{
    "productname":"",
    "keyword1":"",
    "keyword2":"",
    "keyword3":"",
    "brandid":"99",
    "brandValid":"",
    "brandName":"",
    "sellerSzTemplateId":"",
    "selectSzTemplateType":"0",
    "sellerTemplateName":"",
    "functionname_avim":"avim",
    "imagebannername_avim":"",
    "noSpecWholeSaleIncome":"",
    "cateMinPrice":"0.01",
    "noSpecPrice":"",
    "minAkPrice":"",
    "maxAkPrice":"",
    "measureid":"",
    "sortby":"1",
    "packquantity":"1",
    "inventoryLocation":"CN",
    "inventoryStatus":"0",
    "maxSaleQty":"10000",
    "inventory":"",
    "isLeadingtime":"",
    "proLeadingtime":"",
    "setdiscounttype":"",
    "skuCode":"",
    "functionname":"",
    "imagebannername":"",
    "supplierid":"",
    "waterMark":"",
    "imgtoken":"",
    "inp_imgurl":"",
    "inp_imgmd5":"",
    "s_albums_winid":"",
    "pu_imgurl":"",
    "pu_imgmd5":"",
    "pu_localfilename":"",
    "pu_imgsize":"",
    "pu_state":"",
    "puw_albums_winid":"",
    "current_oper_index":"1",
    "current_oper_imgurls":"",
    "googleshoppingimagelist":"",
    "issample_adult":"3",
    "productgroupid":"",
    "productdesc":"",
    "productHtmlmodelid":"",
    "videourl":"",
    "productweight":"0.4",
    "baseqt":"",
    "stepqt":"",
    "stepweight":"",
    "sizelen":"30.0",
    "sizewidth":"20.0",
    "sizeheight":"10.0",
    "shippingmodelname":"标准运费模板",
    "shippingScore":"4",
    "isPostAriMail":"1",
    "vaildday":"30",
    "saleTemplateId":"",
    "saleTemplateName":"LK",
    "rid":"",
    "requestid":"",
    "productid":"",
    "itemcode":"",
    "catepubid":"",
    "imglist":"",
    "prospeclist":"[]",
    "shippingmodelid":"",
    "isquickup":"0",
    "viewSource":"",
    "repeatGroupId":"",
    "oldSkuInfo":"",
    "forEditOldCatePubid":"",
    "proSkuInfo":"",
    "specselfDef":"[]",
    "discountRange":"",
    "productInventorylist":"",
    "sourceItemcode":"",
    "sourceSiteId":"",
    "attrlist":"",
    "tdProSaleSetId":"",
    "sourcetype":"8",
    "recruitActivityId":"",
    "recruitProdPreId":"",
    "attrGroupDetail":"",
    "cmSzTableJson":"",
    "cmszAdviseTableJson":"",
    "szTemplateClassId":"",
    "prodDraftId":"",
    "elm":""
}